zpp_config/__init__.py
zpp_config/cli.py
zpp_config/config.py
zpp_config/backend/__init__.py
zpp_config/backend/cfg.py
zpp_config/backend/global_backend.py
zpp_config/backend/ini.py
zpp_config/backend/json.py
zpp_config/backend/toml.py
zpp_config/backend/yaml.py
zpp_config/core/__init__.py
zpp_config/core/autoreload.py
zpp_config/core/logs.py
zpp_config/core/vault.py
zpp_config/core/vault_encryption.py
zpp_config-2.2.6.dist-info/licenses/LICENSE
zpp_config-2.2.6.dist-info/METADATA
zpp_config-2.2.6.dist-info/WHEEL
zpp_config-2.2.6.dist-info/entry_points.txt
zpp_config-2.2.6.dist-info/top_level.txt
zpp_config-2.2.6.dist-info/RECORD
