Metadata-Version: 2.4
Name: zpp_config
Version: 2.2.6
Summary: Module pour le chargement et la modification de fichier de configuration
Home-page: https://github.com/ZephyrOff/zpp_config
Author: 
License: MIT License
Project-URL: Documentation, https://github.com/ZephyrOff/zpp_config
Keywords: config file terminal zephyroff
Platform: ALL
Classifier: Development Status :: 5 - Production/Stable
Classifier: Environment :: Console
Classifier: License :: OSI Approved :: MIT License
Classifier: Programming Language :: Python :: 3
License-File: LICENSE
Requires-Dist: watchdog
Requires-Dist: pyyaml
Requires-Dist: jinja2
Requires-Dist: impmagic
Requires-Dist: zpp_args
Requires-Dist: zpp_store
Requires-Dist: zpp_color
Requires-Dist: Crypto
Requires-Dist: pycryptodome
Requires-Dist: Cryptography
Requires-Dist: toml
Dynamic: classifier
Dynamic: description
Dynamic: description-content-type
Dynamic: home-page
Dynamic: keywords
Dynamic: license
Dynamic: license-file
Dynamic: platform
Dynamic: project-url
Dynamic: requires-dist
Dynamic: summary
